pymlimageutils/__init__.py
pymlimageutils/pymlimageutils.py
pymlimageutils-0.1.0.dist-info/LICENSE
pymlimageutils-0.1.0.dist-info/METADATA
pymlimageutils-0.1.0.dist-info/WHEEL
pymlimageutils-0.1.0.dist-info/RECORD
