Metadata-Version: 2.1
Name: pymlimageutils
Version: 0.1.0
Summary: This package is useful for checking image data quality, separating image and label files, and splitting datasets.
Home-page: https://github.com/fadedreams/pymlimageutils
License: MIT
Keywords: machine learning,utilities
Author: fadedreams
Author-email: fadedreams7@gmail.com
Requires-Python: >=3.8,<4.0
Classifier: Environment :: Console
Classifier: License :: OSI Approved :: MIT License
Classifier: Operating System :: OS Independent
Classifier: Programming Language :: Python :: 3
Classifier: Programming Language :: Python :: 3.8
Classifier: Programming Language :: Python :: 3.9
Classifier: Programming Language :: Python :: 3.10
Classifier: Programming Language :: Python :: 3.11
Classifier: Programming Language :: Python :: 3
Classifier: Topic :: Utilities
Requires-Dist: opencv-python (>=4.7.0.68,<5.0.0.0)
Requires-Dist: pillow (>=9.4.0,<10.0.0)
Project-URL: Repository, https://github.com/fadedreams/pymlimageutils
